spotify_translator/__init__.py
spotify_translator/constants.py
spotify_translator/spotify_translator.py
spotify_translator/utils.py
spotify_translator-0.0.1.dist-info/METADATA
spotify_translator-0.0.1.dist-info/WHEEL
spotify_translator-0.0.1.dist-info/entry_points.txt
spotify_translator-0.0.1.dist-info/licenses/LICENSE
spotify_translator-0.0.1.dist-info/RECORD
