Metadata-Version: 2.3
Name: spotify-translator
Version: 0.0.1
Summary: Generate lyric translations and transcriptions from Spotify URLs using OpenAI's Whisper model.
Project-URL: Homepage, https://github.com/hajin-park/spotify-translator
Project-URL: Issues, https://github.com/hajin-park/spotify-translator/issues
Author-email: Hajin Park <hajin1819@gmail.com>
License: The MIT License (MIT)
License-File: LICENSE
Keywords: OpenAI,Whisper,spotify,transcript,transcription,transcriptor,translate,translation,translator,youtube,yt
Classifier: Development Status :: 4 - Beta
Classifier: License :: OSI Approved :: MIT License
Classifier: Operating System :: OS Independent
Classifier: Programming Language :: Python :: 3.10
Classifier: Programming Language :: Python :: 3.11
Requires-Python: >=3.10
Requires-Dist: openai-whisper
Requires-Dist: spotify-dl
Requires-Dist: spotipy
